README.md
setup.cfg
setup.py
click_pkg.egg-info/PKG-INFO
click_pkg.egg-info/SOURCES.txt
click_pkg.egg-info/dependency_links.txt
click_pkg.egg-info/requires.txt
click_pkg.egg-info/top_level.txt
click_up/__init__.py
click_up/admin.py
click_up/apps.py
click_up/const.py
click_up/models.py
click_up/urls.py
click_up/views.py
click_up/classes/__init__.py
click_up/classes/client.py
click_up/classes/http.py
click_up/classes/initializer.py
click_up/classes/merchant.py
click_up/exceptions/__init__.py
click_up/migrations/0001_initial.py
click_up/migrations/__init__.py
click_up/typing/__init__.py
click_up/typing/request/__init__.py
click_up/typing/request/shop_api.py
click_up/typing/response/__init__.py
click_up/typing/response/shop_api.py
clickup_fastapi/__init__.py
clickup_fastapi/dependencies.py
clickup_fastapi/api/__init__.py
clickup_fastapi/api/webhook.py
clickup_fastapi/core/__init__.py
clickup_fastapi/core/client.py
clickup_fastapi/core/http.py
clickup_fastapi/core/initializer.py
clickup_fastapi/core/merchant.py
clickup_fastapi/models/__init__.py
clickup_fastapi/models/transaction.py
clickup_fastapi/schemas/__init__.py
clickup_fastapi/schemas/request.py
clickup_fastapi/schemas/response.py
clickup_fastapi/utils/__init__.py
clickup_fastapi/utils/auth.py
clickup_fastapi/utils/const.py
clickup_fastapi/utils/exceptions.py