Metadata-Version: 2.4
Name: click-pkg
Version: 0.15
Summary: Python package for Click payment gateway integration
Home-page: https://github.com/Muhammadali-Akbarov/click-pkg
Author: Muhammadali Akbarov
Author-email: muhammadali17abc@gmail.com
License: MIT
Keywords: click-shop-api,click,click-merchant,click-pkg,click-api,click-python-integration,click-integration,click-python,click-gateway,click-payment,click-payment-gateway,click-integration-python,click-api-client,click-django,click-rest-api,click-fastapi
Classifier: Development Status :: 4 - Beta
Classifier: Intended Audience :: Developers
Classifier: Programming Language :: Python :: 3
Classifier: Programming Language :: Python :: 3.6
Classifier: Programming Language :: Python :: 3.7
Classifier: Programming Language :: Python :: 3.8
Classifier: Programming Language :: Python :: 3.9
Classifier: Programming Language :: Python :: 3.10
Classifier: Programming Language :: Python :: 3.11
Classifier: Programming Language :: Python :: 3.12
Classifier: License :: OSI Approved :: MIT License
Classifier: Operating System :: OS Independent
Classifier: Topic :: Software Development :: Libraries :: Python Modules
Requires-Python: >=3.6
Requires-Dist: requests<3.0,>=2.0
Requires-Dist: dataclasses<1.0,>=0.6; python_version < "3.7"
Provides-Extra: django
Requires-Dist: django<5.0,>=3.0; extra == "django"
Requires-Dist: djangorestframework<4.0,>=3.0; extra == "django"
Provides-Extra: fastapi
Requires-Dist: sqlalchemy<3.0,>=1.4; extra == "fastapi"
Requires-Dist: httpx<1.0,>=0.20; extra == "fastapi"
Requires-Dist: python-multipart==0.0.20; extra == "fastapi"
Requires-Dist: pydantic<2.0,>=1.8; extra == "fastapi"
Dynamic: author
Dynamic: author-email
Dynamic: classifier
Dynamic: description
Dynamic: description-content-type
Dynamic: home-page
Dynamic: keywords
Dynamic: license
Dynamic: provides-extra
Dynamic: requires-dist
Dynamic: requires-python
Dynamic: summary
